MANIFEST.in
VERSION
distribute_setup.py
setup.py
lib/relations/__init__.py
lib/relations/relation.py
lib/relations/tuple.py
lib/relations.egg-info/PKG-INFO
lib/relations.egg-info/SOURCES.txt
lib/relations.egg-info/dependency_links.txt
lib/relations.egg-info/requires.txt
lib/relations.egg-info/top_level.txt
test/test_joins.py
test/test_relation.py
test/test_set_operations.py