Metadata-Version: 1.0
Name: relations
Version: 0.0.2
Summary: A simple relational algebra engine in Python.
Home-page: http://github.com/zacharyvoase/relations
Author: Zachary Voase
Author-email: z@zacharyvoase.com
License: UNKNOWN
Platform: UNKNOWN
